MANIFEST.in
README.md
requirements.dev.txt
requirements.test.txt
requirements.txt
setup.py
http_firewall/__init__.py
http_firewall/__main__.py
http_firewall/acl.py
http_firewall/logging.py
http_firewall/main.py
tornado_http_firewall.egg-info/PKG-INFO
tornado_http_firewall.egg-info/SOURCES.txt
tornado_http_firewall.egg-info/dependency_links.txt
tornado_http_firewall.egg-info/entry_points.txt
tornado_http_firewall.egg-info/requires.txt
tornado_http_firewall.egg-info/top_level.txt