Metadata-Version: 2.1
Name: tornado-http-firewall
Version: 0.0.3
Summary: Validation and Hosting daemon for scatter.online.
Home-page: https://github.com/mikeshultz/scatter-daemon
Author: Mike Shultz
Author-email: mike@gointo.software
License: UNKNOWN
Keywords: ipfs ethereum
Platform: UNKNOWN
Classifier: Development Status :: 3 - Alpha
Classifier: Intended Audience :: End Users/Desktop
Classifier: Topic :: Internet
Classifier: Topic :: System :: Filesystems
Classifier: License :: OSI Approved :: GNU General Public License v3 or later (GPLv3+)
Classifier: Programming Language :: Python :: 3
Classifier: Programming Language :: Python :: 3.4
Classifier: Programming Language :: Python :: 3.5
Classifier: Programming Language :: Python :: 3.6
Provides-Extra: dev
Provides-Extra: test
